Lang2Logic/__init__.py
Lang2Logic/data_manager.py
Lang2Logic/generate_draft_7.py
Lang2Logic/generate_response.py
Lang2Logic/generator.py
Lang2Logic/model_unwrap.py
Lang2Logic/response_schema.py
Lang2Logic-1.2.0.dist-info/LICENSE
Lang2Logic-1.2.0.dist-info/METADATA
Lang2Logic-1.2.0.dist-info/WHEEL
Lang2Logic-1.2.0.dist-info/top_level.txt
Lang2Logic-1.2.0.dist-info/RECORD
