Metadata-Version: 2.1
Name: Lang2Logic
Version: 1.2.0
Summary: A package for generating, validating, and utilizing Draft-7 JSON schemas with LangChain
Author: Dylan Wilson
Author-email: dylanpwilson2005@gmail.com
License: CC0-1.0
Keywords: language models,structured output
Classifier: Development Status :: 3 - Alpha
Classifier: Intended Audience :: Developers
Classifier: License :: Other/Proprietary License
Classifier: Programming Language :: Python :: 3
Classifier: Programming Language :: Python :: 3.11
Requires-Python: >=3.7, <4
License-File: LICENSE
Requires-Dist: langchain ==0.0.350
Requires-Dist: langchain-community ==0.0.2
Requires-Dist: pydantic ==2.5.0
Requires-Dist: jsonschema ==4.20.0
Requires-Dist: openai ==1.6.1
Provides-Extra: dev
Requires-Dist: check-manifest ; extra == 'dev'
Provides-Extra: test
Requires-Dist: coverage ; extra == 'test'
